shanbay_assistant/__init__.py
shanbay_assistant/assistant.py
shanbay_assistant/conf.py
shanbay_assistant/utils.py
shanbay_assistant-0.3.0.dist-info/DESCRIPTION.rst
shanbay_assistant-0.3.0.dist-info/entry_points.txt
shanbay_assistant-0.3.0.dist-info/METADATA
shanbay_assistant-0.3.0.dist-info/metadata.json
shanbay_assistant-0.3.0.dist-info/RECORD
shanbay_assistant-0.3.0.dist-info/top_level.txt
shanbay_assistant-0.3.0.dist-info/WHEEL
