Metadata-Version: 2.0
Name: shanbay-assistant
Version: 0.3.0
Summary: shanbay.com team assistant
Home-page: https://github.com/mozillazg/python-shanbay-team-assistant
Author: mozillazg
Author-email: mozillazg101@gmail.com
License: MIT
Keywords: shanbay,扇贝网
Platform: UNKNOWN
Classifier: Development Status :: 5 - Production/Stable
Classifier: Intended Audience :: Developers
Classifier: License :: OSI Approved :: MIT License
Classifier: Operating System :: OS Independent
Classifier: Programming Language :: Python
Classifier: Programming Language :: Python :: 2
Classifier: Programming Language :: Python :: 2.6
Classifier: Programming Language :: Python :: 2.7
Classifier: Environment :: Console
Classifier: Topic :: Utilities
Classifier: Topic :: Terminals
Requires-Dist: argparse
Requires-Dist: shanbay (==0.3.6)
